raic/foundry/datasources.py
raic/foundry/inference.py
raic/foundry/models.py
raic/foundry/raic_vision.py
raic/foundry/cli/console.py
raic/foundry/cli/initialize.py
raic/foundry/cli/raic_cli.py
raic/foundry/client/context.py
raic/foundry/client/datasource.py
raic/foundry/client/embedding.py
raic/foundry/client/environment.py
raic/foundry/client/image.py
raic/foundry/client/inference_job.py
raic/foundry/client/model.py
raic/foundry/client/raic_authenticator.py
raic/foundry/client/raic_client_base.py
raic/foundry/client/raic_configuration.py
raic/foundry/client/raic_vision_job.py
raic/foundry/client/request.py
raic/foundry/client/user.py
raic/foundry/configuration/raic-configuration.json
raic/foundry/configuration/raic-configuration.json.template
raic/foundry/entities/artifacts.py
raic/foundry/entities/manifests.py
raic/foundry/inputs/archive.py
raic/foundry/inputs/datasource.py
raic/foundry/inputs/exif.py
raic/foundry/inputs/geospatial.py
raic/foundry/inputs/image.py
raic/foundry/inputs/manifest.py
raic/foundry/results/embedding.py
raic/foundry/results/faiss_index.py
raic/foundry/shared/azure.py
raic/foundry/shared/utils.py
raic_foundry-2025.4.11.0.dist-info/METADATA
raic_foundry-2025.4.11.0.dist-info/WHEEL
raic_foundry-2025.4.11.0.dist-info/entry_points.txt
raic_foundry-2025.4.11.0.dist-info/top_level.txt
raic_foundry-2025.4.11.0.dist-info/RECORD
