Metadata-Version: 2.4
Name: raic-foundry
Version: 2025.4.11.0
Summary: raic-foundry
Keywords: raic,foundry
Classifier: Programming Language :: Python :: 3
Classifier: Programming Language :: Python :: 3.10
Classifier: Programming Language :: Python :: 3.11
Classifier: Programming Language :: Python :: 3.12
Requires-Python: >=3.10
Requires-Dist: wheel==0.45.0
Requires-Dist: pyparsing==3.2.0
Requires-Dist: cython==3.0.11
Requires-Dist: tqdm==4.67.0
Requires-Dist: dill==0.3.9
Requires-Dist: opencv-contrib-python-headless==4.10.0.84
Requires-Dist: patool==3.0.3
Requires-Dist: pydantic==2.9.2
Requires-Dist: pandas==2.2.3
Requires-Dist: numpy==1.26.4
Requires-Dist: pillow==11.1.0
Requires-Dist: python-dotenv==1.0.1
Requires-Dist: seaborn==0.13.2
Requires-Dist: faiss-cpu==1.8.0
Requires-Dist: auth0-python==4.7.2
Requires-Dist: azure-storage-blob==12.24.0
Requires-Dist: gitpython==3.1.43
Requires-Dist: rasterio==1.4.2
Requires-Dist: rio-tiler==7.5.0
Requires-Dist: shapely==2.0.6
Requires-Dist: typer==0.13.1
Requires-Dist: pytest
